unique_log_question_app/__init__.py
unique_log_question_app/admin.py
unique_log_question_app/apps.py
unique_log_question_app/decorators.py
unique_log_question_app/forms.py
unique_log_question_app/models.py
unique_log_question_app/tests.py
unique_log_question_app/urls.py
unique_log_question_app/views.py
unique_log_question_app/migrations/__init__.py
unique_log_question_app/templates/edit_chat_sessions.html
unique_log_question_app/templates/edit_similar_questions.html
unique_log_question_app/templates/log_questions.html
unique_log_question_app/templates/unique_questions.html
unique_log_question_project/__init__.py
unique_log_question_project/asgi.py
unique_log_question_project/settings.py
unique_log_question_project/urls.py
unique_log_question_project/wsgi.py
unique_log_questions-0.19.data/data/README.md
unique_log_questions-0.19.data/data/requirements.txt
unique_log_questions-0.19.dist-info/LICENSE
unique_log_questions-0.19.dist-info/METADATA
unique_log_questions-0.19.dist-info/WHEEL
unique_log_questions-0.19.dist-info/entry_points.txt
unique_log_questions-0.19.dist-info/top_level.txt
unique_log_questions-0.19.dist-info/RECORD
