Metadata-Version: 2.1
Name: unique-log-questions
Version: 0.19
Summary: A Django app for chatbot functionality.
Home-page: https://github.com/saini2001/chatbot_code
Author: Swati Saini
Author-email: swati@mixorg.com
Classifier: Framework :: Django
Classifier: Programming Language :: Python :: 3.11
License-File: LICENSE
